LaunchTelemetry.py
README.txt
setup.py
dronekit_texting/TextMessageTelemetry.py
dronekit_texting/__init__.py
dronekit_textmessaging.egg-info/PKG-INFO
dronekit_textmessaging.egg-info/SOURCES.txt
dronekit_textmessaging.egg-info/dependency_links.txt
dronekit_textmessaging.egg-info/requires.txt
dronekit_textmessaging.egg-info/top_level.txt