Metadata-Version: 1.1
Name: dronekit-textmessaging
Version: 1.0.1
Summary: Text Messaging Telemetry for DroneKit
Home-page: https://github.com/Chambana/DroneKit-TextMessageTelemetry
Author: Chambana
Author-email: Chambana03@gmail.com
License: GNU GPL
Keywords: dronekit quadcopter rover plane drone pixhawk APM SMS text messaging
Platform: UNKNOWN
Classifier: Development Status :: 4 - Beta
Classifier: Intended Audience :: End Users/Desktop
Classifier: Topic :: Communications
Classifier: License :: OSI Approved :: GNU Lesser General Public License v3 (LGPLv3)
Classifier: Programming Language :: Python :: 2
Classifier: Programming Language :: Python :: 2.6
Classifier: Programming Language :: Python :: 2.7
